googlemail/__init__.py
googlemail/config.py
googlemail/gmail.py
googlemail/login.py
googlemail-0.1.0.dist-info/LICENSE.txt
googlemail-0.1.0.dist-info/METADATA
googlemail-0.1.0.dist-info/WHEEL
googlemail-0.1.0.dist-info/top_level.txt
googlemail-0.1.0.dist-info/RECORD
