Metadata-Version: 2.1
Name: googlemail
Version: 0.1.0
Summary: Gmail client
Home-page: https://github.com/orlandodiaz/googlemail
Author: Orlando Diaz
Author-email: orlandodiaz.dev@gmail.com
License: UNKNOWN
Platform: UNKNOWN
Classifier: Programming Language :: Python :: 3
Classifier: License :: OSI Approved :: MIT License
Classifier: Operating System :: OS Independent
